Metadata-Version: 2.1
Name: py_find_1st
Version: 1.1.7
Summary: Numpy extension module for efficient search of first array index that compares true
Author-email: "A. Roebel" <axel.roebel@ircam.fr>
License: GPL
Project-URL: homepage, https://github.com/roebel/py_find_1st
Project-URL: repository, https://github.com/roebel/py_find_1st
Keywords: numpy,extension,find
Classifier: Topic :: Software Development :: Libraries :: Python Modules
Classifier: Programming Language :: Python :: 3
Classifier: Development Status :: 5 - Production/Stable
Classifier: License :: OSI Approved :: GNU General Public License (GPL)
Classifier: Operating System :: MacOS :: MacOS X
Classifier: Operating System :: POSIX :: Linux
Classifier: Operating System :: Microsoft :: Windows
License-File: COPYING.txt
Requires-Dist: numpy<2.0,>=1.13.0; python_version <= "3.8"
Requires-Dist: numpy<3,>=1.19.3; python_version > "3.8"
